om_api_client/__init__.py
om_api_client/om_api_client.py
om_api_client-0.0.0.dev2.dist-info/METADATA
om_api_client-0.0.0.dev2.dist-info/WHEEL
om_api_client-0.0.0.dev2.dist-info/entry_points.txt
om_api_client-0.0.0.dev2.dist-info/top_level.txt
om_api_client-0.0.0.dev2.dist-info/RECORD
