Metadata-Version: 2.4
Name: om-api-client
Version: 0.0.0.dev2
Summary: OGC Observations & Measurements  REST API (compliant with OM-JSON OGC DP 15-100r1 and GeoJSON, used by WMO WHOS DAB) client. Part of WMO HydroSOS project
Author-email: SSIyAH-INA <jbianchi@ina.gob.ar>
Project-URL: Homepage, https://github.com/wmo-im/HydroSOS
Classifier: Programming Language :: Python :: 3
Classifier: License :: OSI Approved :: MIT License
Classifier: Operating System :: OS Independent
Requires-Python: >=3.8
Requires-Dist: click
Requires-Dist: plotly
Requires-Dist: nbformat
Requires-Dist: pandas
Requires-Dist: requests
Requires-Dist: pyyaml
